setup.cfg
setup.py
openapi_generator/__init__.py
openapi_generator/openapi_generator.py
openapi_generator/run.py
openapi_generator/test_generator.py
openapi_generator.egg-info/PKG-INFO
openapi_generator.egg-info/SOURCES.txt
openapi_generator.egg-info/dependency_links.txt
openapi_generator.egg-info/requires.txt
openapi_generator.egg-info/top_level.txt