Metadata-Version: 1.1
Name: openapi-generator
Version: 1.0.4
Summary: A library to generate OpenAPI documentation from requests
Home-page: https://github.com/wael34218/python_openapi_generator
Author: Wael Farhan
Author-email: wael34218@gmail.com
License: UNKNOWN
Download-URL: https://github.com/wael34218/python_openapi_generator/archive/v1.0.4.tar.gz
Keywords: flask framework base class generic
Platform: UNKNOWN
Classifier: Operating System :: OS Independent
Classifier: Programming Language :: Python :: 3.5
Classifier: License :: OSI Approved :: MIT License
